QuantGYMM/__init__.py
QuantGYMM/calendar.py
QuantGYMM/descriptors.py
QuantGYMM/instruments.py
QuantGYMM/models.py
QuantGYMM/pricers.py
QuantGYMM/term_structures.py
QuantGYMM/utils.py
QuantGYMM/test/__init__.py
QuantGYMM/test/test_descriptors.py
QuantGYMM/test/test_function.py
QuantGYMM-0.2.dist-info/LICENSE
QuantGYMM-0.2.dist-info/METADATA
QuantGYMM-0.2.dist-info/WHEEL
QuantGYMM-0.2.dist-info/top_level.txt
QuantGYMM-0.2.dist-info/RECORD
