Metadata-Version: 2.1
Name: QuantGYMM
Version: 0.2
Summary: Package for dealing with bond pricing and hedging
Home-page: https://github.com/GianlucaBroll95/QuantGYMM
Author: Gianluca Broll
Author-email: Gianluca Broll <gianluca.broll@gmail.com>
Project-URL: Homepage, https://github.com/GianlucaBroll95/QuantGYMM
Classifier: Programming Language :: Python :: 3
Classifier: License :: OSI Approved :: MIT License
Classifier: Operating System :: OS Independent
Requires-Python: >3.9
License-File: LICENSE
Requires-Dist: pandas
Requires-Dist: numpy
Requires-Dist: scipy
